{
  "medicine": [
    {
      "id": 517,
      "name": "Binal1",
      "Price": "654",
      "quantity": "100",
      "expiry": "2022"
    },
    {
      "id": 983,
      "name": "Binal",
      "Price": "654",
      "quantity": "100",
      "expiry": "2022"
    },
    {
      "id": 640,
      "name": "Binalb",
      "Price": "565",
      "quantity": "300",
      "expiry": "2023"
    },
    {
      "id": 921,
      "name": "Binal Bodar",
      "Price": "5651",
      "quantity": "300",
      "expiry": "20251"
    }
  ],
  "comments": [
    {
      "id": 1,
      "title": "json",
      "author": "typicode"
    },
    {
      "id": 123,
      "title": "json232",
      "author": "typicode2123"
    }
  ],
  "profile": {
    "id": 1,
    "title": "json",
    "author": "typicode"
  }
}